MANIFEST.in
setup.py
impaf_auth.egg-info/PKG-INFO
impaf_auth.egg-info/SOURCES.txt
impaf_auth.egg-info/dependency_links.txt
impaf_auth.egg-info/namespace_packages.txt
impaf_auth.egg-info/not-zip-safe
impaf_auth.egg-info/requires.txt
impaf_auth.egg-info/top_level.txt
implugin/__init__.py
implugin/auth/__init__.py
implugin/auth/application.py
implugin/auth/controllers.py
implugin/auth/db_tables.py
implugin/auth/driver.py
implugin/auth/entry.py
implugin/auth/forms.py
implugin/auth/model_base.py
implugin/auth/models.py
implugin/auth/requestable.py
implugin/auth/testing.py
implugin/auth/widgets.py
implugin/auth/templates/forbidden.jinja2
implugin/auth/templates/login.jinja2
implugin/auth/templates/register.jinja2
implugin/auth/templates/forms/password.jinja2
implugin/auth/templates/forms/text.jinja2
implugin/auth/tests/__init__.py
implugin/auth/tests/test_application.py
implugin/auth/tests/test_controllers.py
implugin/auth/tests/test_driver.py
implugin/auth/tests/test_entry.py
implugin/auth/tests/test_forbidden_controller.py
implugin/auth/tests/test_forms.py
implugin/auth/tests/test_login_controller.py
implugin/auth/tests/test_logout_controller.py
implugin/auth/tests/test_models.py
implugin/auth/tests/test_register_controller.py
implugin/auth/tests/test_requestable.py
implugin/auth/tests/test_widgets.py