Metadata-Version: 1.0
Name: impaf-auth
Version: 0.1.1
Summary: Flash Message plugin for Impaf.
Home-page: UNKNOWN
Author: UNKNOWN
Author-email: UNKNOWN
License: Apache License 2.0
Platform: UNKNOWN
